{
  "name" : "HD motorisée",
  "manufacturer" : "Mustcam",
  "configuration": {
    "port": "80",
    "urlStream": "\/snapshot.cgi?usr=#username#&pwd=#password#",
    "protocole": "http"
  },
  "commands": [
    {
      "eqType": "camera",
      "name": "Bas",
      "type": "action",
      "subType": "other",
      "isHistorized": "0",
      "configuration": {
        "request": "\/media/?action=cmd&code=2&value=2",
        "stopCmdUrl": "\/media/?action=cmd&code=3&value=2"
      },
      "display": {
        "icon": "<i class=\"fas fa-arrow-down\"><\/i>",
        "generic_type": "CAMERA_DOWN"
      },
      "isVisible": "1"
    },
    {
      "eqType": "camera",
      "name": "Haut",
      "type": "action",
      "subType": "other",
      "isHistorized": "0",
      "configuration": {
        "request": "\/media/?action=cmd&code=2&value=1",
        "stopCmdUrl": "\/media/?action=cmd&code=3&value=1"
      },
      "display": {
        "icon": "<i class=\"fas fa-arrow-up\"><\/i>",
        "generic_type": "CAMERA_UP"
      },
      "isVisible": "1"
    },
    {
      "eqType": "camera",
      "name": "Gauche",
      "type": "action",
      "subType": "other",
      "isHistorized": "0",
      "configuration": {
        "request": "\/media/?action=cmd&code=2&value=4",
        "stopCmdUrl": "\/media/?action=cmd&code=3&value=4"
      },
      "display": {
        "icon": "<i class=\"fas fa-arrow-left\"><\/i>",
        "generic_type": "CAMERA_LEFT"
      },
      "isVisible": "1"
    },
    {
      "eqType": "camera",
      "name": "Droite",
      "type": "action",
      "subType": "other",
      "isHistorized": "0",
      "configuration": {
        "request": "\/media/?action=cmd&code=2&value=3",
        "stopCmdUrl": "\/media/?action=cmd&code=3&value=3"
      },
      "display": {
        "icon": "<i class=\"fas fa-arrow-right\"><\/i>",
        "generic_type": "CAMERA_RIGHT"
      },
      "isVisible": "1"
    },
    {
      "eqType": "camera",
      "name": "Preset 1",
      "type": "action",
      "subType": "other",
      "isHistorized": "0",
      "configuration": {
        "request": "\/media/?action=cmd&code=13&value=1",
        "stopCmdUrl": "0"
      },
      "isVisible": "0"
    },
    {
      "eqType": "camera",
      "name": "Preset 2",
      "type": "action",
      "subType": "other",
      "isHistorized": "0",
      "configuration": {
        "request": "\/media/?action=cmd&code=13&value=2",
        "stopCmdUrl": "0"
      },
      "isVisible": "0"
    },
    {
      "eqType": "camera",
      "name": "Preset 3",
      "type": "action",
      "subType": "other",
      "isHistorized": "0",
      "configuration": {
        "request": "\/media/?action=cmd&code=13&value=3",
        "stopCmdUrl": "0"
      },
      "isVisible": "0"
    },
    {
      "eqType": "camera",
      "name": "Preset 4",
      "type": "action",
      "subType": "other",
      "isHistorized": "0",
      "configuration": {
        "request": "\/media/?action=cmd&code=13&value=4",
        "stopCmdUrl": "0"
      },
      "isVisible": "0"
    },
    {
      "eqType": "camera",
      "name": "Preset 5",
      "type": "action",
      "subType": "other",
      "isHistorized": "0",
      "configuration": {
        "request": "\/media/?action=cmd&code=13&value=5",
        "stopCmdUrl": "0"
      },
      "isVisible": "0"
    },
    {
      "eqType": "camera",
      "name": "Preset 6",
      "type": "action",
      "subType": "other",
      "isHistorized": "0",
      "configuration": {
        "request": "\/media/?action=cmd&code=13&value=6",
        "stopCmdUrl": "0"
      },
      "isVisible": "0"
    },
    {
      "eqType": "camera",
      "name": "Patrouille horizontale",
      "type": "action",
      "subType": "other",
      "isHistorized": "0",
      "configuration": {
        "request": "\/media/?action=cmd&code=2&value=9",
        "stopCmdUrl": "0"
      },
      "isVisible": "0"
    },
    {
      "eqType": "camera",
      "name": "Patrouille verticale",
      "type": "action",
      "subType": "other",
      "isHistorized": "0",
      "configuration": {
        "request": "\/media/?action=cmd&code=2&value=10",
        "stopCmdUrl": "0"
      },
      "isVisible": "0"
    },
    {
      "eqType": "camera",
      "name": "Stop horizontale",
      "type": "action",
      "subType": "other",
      "isHistorized": "0",
      "configuration": {
        "request": "\/decoder_control.cgi?command=29&user=#username#&pwd=#password#",
        "stopCmdUrl": "\/media/?action=cmd&code=3&value=4"
      },
      "isVisible": "0"
    },
    {
      "eqType": "camera",
      "name": "Stop verticale",
      "type": "action",
      "subType": "other",
      "isHistorized": "0",
      "configuration": {
        "request": "\/decoder_control.cgi?command=27&user=#username#&pwd=#password#",
        "stopCmdUrl": "\/media/?action=cmd&code=3&value=1"
      },
      "isVisible": "0"
    },
    {
      "eqType": "camera",
      "name": "Tour",
      "type": "action",
      "subType": "other",
      "isHistorized": "0",
      "configuration": {
        "request": "\/media/?action=cmd&code=2&value=11",
        "stopCmdUrl": "0"
      },
      "isVisible": "0"
    }
  ]
}
